fastQpick/__init__.py
fastQpick/_version.py
fastQpick/main.py
fastQpick/utils.py
fastQpick-0.1.0.dist-info/LICENSE
fastQpick-0.1.0.dist-info/METADATA
fastQpick-0.1.0.dist-info/WHEEL
fastQpick-0.1.0.dist-info/entry_points.txt
fastQpick-0.1.0.dist-info/top_level.txt
fastQpick-0.1.0.dist-info/RECORD
