Metadata-Version: 2.2
Name: fastQpick
Version: 0.1.0
Summary: Fast and memory-efficient sampling of DNA-Seq or RNA-seq fastq data with or without replacement.
Author-email: Joseph Rich <josephrich98@gmail.com>
Maintainer-email: Joseph Rich <josephrich98@gmail.com>
License: BSD 2-Clause License
Project-URL: Homepage, https://github.com/pachterlab/fastQpick
Keywords: fastQpick,bioinformatics,statistics,RNA-seq,DNA-seq
Classifier: Environment :: Console
Classifier: Framework :: Jupyter
Classifier: Intended Audience :: Science/Research
Classifier: License :: OSI Approved :: BSD License
Classifier: Operating System :: OS Independent
Classifier: Programming Language :: Python :: 3.9
Classifier: Programming Language :: Python :: 3.10
Classifier: Programming Language :: Python :: 3.11
Classifier: Programming Language :: Python :: 3.12
Classifier: Topic :: Scientific/Engineering :: Bio-Informatics
Classifier: Topic :: Utilities
Requires-Python: >=3.7
License-File: LICENSE
Requires-Dist: pyfastx>=2.0.0
Requires-Dist: tqdm>=4.66.0
